setup.py
Mensuration/Area_2D.py
Mensuration/Error_Handler.py
Mensuration/Parameters.py
Mensuration/Volume.py
Mensuration/__init__.py
Mensuration.egg-info/PKG-INFO
Mensuration.egg-info/SOURCES.txt
Mensuration.egg-info/dependency_links.txt
Mensuration.egg-info/not-zip-safe
Mensuration.egg-info/top_level.txt