Metadata-Version: 1.0
Name: Mensuration
Version: 1.1
Summary: Mensuration tools
Home-page: UNKNOWN
Author: Rahul Rajeev Pillai
Author-email: rahulpillai0128@gmail.com
License: license.txt
Platform: Windows
Platform: Linux
Platform: MacOs
